README.rst
setup.py
realexpayments/__init__.py
realexpayments/client.py
realexpayments/domain.py
realexpayments/exceptions.py
realexpayments/utils.py
realexpayments.egg-info/PKG-INFO
realexpayments.egg-info/SOURCES.txt
realexpayments.egg-info/dependency_links.txt
realexpayments.egg-info/requires.txt
realexpayments.egg-info/top_level.txt