Metadata-Version: 1.1
Name: realexpayments
Version: 1.2.0
Summary: Realex Payments SDK for Python
Home-page: https://github.com/viniciuschiele/realex-sdk
Author: Vinicius Chiele
Author-email: vinicius.chiele@gmail.com
License: MIT
Keywords: realex,payments,api,client
Platform: UNKNOWN
Classifier: Development Status :: 5 - Production/Stable
Classifier: Intended Audience :: Developers
Classifier: Natural Language :: English
Classifier: Operating System :: OS Independent
Classifier: Programming Language :: Python
Classifier: Programming Language :: Python :: 2.7
Classifier: Programming Language :: Python :: 3
Classifier: Programming Language :: Python :: 3.2
Classifier: Programming Language :: Python :: 3.3
Classifier: Programming Language :: Python :: 3.4
Classifier: Programming Language :: Python :: Implementation :: CPython
